object_detection/__init__.py
object_detection/detect_image.py
object_detection/yolo_detector.py
object_detection/models/__init__.py
object_detection/models/common.py
object_detection/models/experimental.py
object_detection/models/tf.py
object_detection/models/yolo.py
object_detection/utils/__init__.py
object_detection/utils/activations.py
object_detection/utils/augmentations.py
object_detection/utils/autoanchor.py
object_detection/utils/autobatch.py
object_detection/utils/callbacks.py
object_detection/utils/datasets.py
object_detection/utils/downloads.py
object_detection/utils/general.py
object_detection/utils/log_conf.py
object_detection/utils/loss.py
object_detection/utils/metrics.py
object_detection/utils/plots.py
object_detection/utils/torch_utils.py
object_detection/utils/loggers/__init__.py
object_detection_yolo-0.0.2.dist-info/METADATA
object_detection_yolo-0.0.2.dist-info/WHEEL
object_detection_yolo-0.0.2.dist-info/top_level.txt
object_detection_yolo-0.0.2.dist-info/RECORD
